zvma10/__init__.py
zvma10/test.py
zvma10/version.py
zvma10/zvma.py
zvma10_api_wrapper-1.0.0.dist-info/LICENSE
zvma10_api_wrapper-1.0.0.dist-info/METADATA
zvma10_api_wrapper-1.0.0.dist-info/WHEEL
zvma10_api_wrapper-1.0.0.dist-info/top_level.txt
zvma10_api_wrapper-1.0.0.dist-info/RECORD
